MANIFEST.in
README.md
setup.py
ProcessHandler/__init__.py
ProcessHandler.egg-info/PKG-INFO
ProcessHandler.egg-info/SOURCES.txt
ProcessHandler.egg-info/dependency_links.txt
ProcessHandler.egg-info/requires.txt
ProcessHandler.egg-info/top_level.txt